<?xml version="1.0" encoding="utf-8"?>
<profiles xmlns="http://www.logitech.com/Cassandra/2010.7/Profile">
  <profile gkeysdk="0" gpasupported="0" lock="0" lastplayeddate="2020-10-20T18:27:47" name="Minecraft" launchable="1" gameid="" guid="{5B73AEA4-1670-401F-B4AA-9FC34D90E2F8}">
    <description></description>
    <target path="E:\GAMES\MINECRAFT\RUNTIME\JRE-X64\BIN\JAVAW.EXE"/>
    <signature key="" name="" value="" executable=""/>
    <macros>
      <macro name="Left Click" hidden="false" color="4278246655" guid="{5DAFA657-7E0B-4D37-9F7A-FA252ED551E6}">
        <mousefunction xmlns="http://www.logitech.com/Cassandra/2010.1/Macros/MouseFunction">
          <do task="leftclick"/>
        </mousefunction>
      </macro>
      <macro name="Right Click" hidden="false" color="4278246655" guid="{9D0F4485-F6CE-49AF-B3FB-328DBF996F1E}">
        <mousefunction xmlns="http://www.logitech.com/Cassandra/2010.1/Macros/MouseFunction">
          <do task="rightclick"/>
        </mousefunction>
      </macro>
      <macro name="Middle Click" hidden="false" color="4278246655" guid="{8B615B23-6FDC-4430-9E57-E5CCBCAC4575}">
        <mousefunction xmlns="http://www.logitech.com/Cassandra/2010.1/Macros/MouseFunction">
          <do task="middleclick"/>
        </mousefunction>
      </macro>
      <macro name="Walk" hidden="false" color="4278246655" guid="{8B13562D-60F2-460F-9588-8C84168C81BC}">
        <keystroke xmlns="http://www.logitech.com/Cassandra/2010.1/Macros/Keystroke">
          <key value="W"/>
        </keystroke>
      </macro>
      <macro name="Backwards" hidden="false" color="4278246655" guid="{12C9716B-4D7A-4F6F-AF20-A0369219119A}">
        <keystroke xmlns="http://www.logitech.com/Cassandra/2010.1/Macros/Keystroke">
          <key value="S"/>
        </keystroke>
      </macro>
      <macro name="Jump" hidden="false" color="4278246655" guid="{68A1C0B2-2996-4992-9CC5-3285AC8E9740}">
        <keystroke xmlns="http://www.logitech.com/Cassandra/2010.1/Macros/Keystroke">
          <key value="SPACEBAR"/>
        </keystroke>
      </macro>
      <macro repeatmode="pressed" name="Bucket Spam" repeatdelay="5" hidden="false" color="4278246655" guid="{A1FEC5BC-9A8A-49C5-B085-0E2EDCEF1F55}">
        <multikey xmlns="http://www.logitech.com/Cassandra/2010.1/Macros/MultiKey">
          <mousebutton button="right" direction="down"/>
          <mousebutton button="right" direction="up"/>
        </multikey>
      </macro>
      <macro repeatmode="toggle" name="HOLD RIGHT" repeatdelay="0" hidden="false" color="4278246655" guid="{8CE9CC65-F86E-4F6E-ACF8-1A28F64B7FA2}">
        <multikey xmlns="http://www.logitech.com/Cassandra/2010.1/Macros/MultiKey">
          <mousebutton button="right" direction="down"/>
        </multikey>
      </macro>
      <macro repeatmode="toggle" name="1 second clicker" repeatdelay="1000" hidden="false" color="4278246655" guid="{A0D817F6-1D5D-483B-ADD0-2634CD93D42A}">
        <multikey xmlns="http://www.logitech.com/Cassandra/2010.1/Macros/MultiKey">
          <mousebutton button="left" direction="down"/>
          <mousebutton button="left" direction="up"/>
        </multikey>
      </macro>
      <macro name="Next Track" hidden="false" color="4278246655" guid="{EE4405FC-1722-4567-A8D3-A2E2A55FDB4F}">
        <media xmlns="http://www.logitech.com/Cassandra/2010.1/Macros/Media">
          <do task="nexttrack"/>
        </media>
      </macro>
      <macro name="Previous Track" hidden="false" color="4278246655" guid="{C0C50E2E-DC80-4C90-85E7-D3FAA614A39E}">
        <media xmlns="http://www.logitech.com/Cassandra/2010.1/Macros/Media">
          <do task="previoustrack"/>
        </media>
      </macro>
      <macro repeatmode="toggle" name="Play/Pause" repeatdelay="120000" hidden="false" color="4278246655" guid="{9D0036D1-FF58-4DCF-B8FB-17940F29BB6F}">
        <media xmlns="http://www.logitech.com/Cassandra/2010.1/Macros/Media">
          <do task="playpause"/>
        </media>
      </macro>
    </macros>
    <assignments devicecategory="Logitech.Gaming.Mouse.C08B">
      <assignment backup="false" original="false" shiftstate="1" contextid="Button1" macroguid="{5DAFA657-7E0B-4D37-9F7A-FA252ED551E6}"/>
      <assignment backup="false" original="false" shiftstate="1" contextid="Button2" macroguid="{9D0F4485-F6CE-49AF-B3FB-328DBF996F1E}"/>
      <assignment backup="false" original="false" shiftstate="1" contextid="Button3" macroguid="{8B615B23-6FDC-4430-9E57-E5CCBCAC4575}"/>
      <assignment backup="false" original="false" shiftstate="1" contextid="Button5" macroguid="{8B13562D-60F2-460F-9588-8C84168C81BC}"/>
      <assignment backup="false" original="false" shiftstate="1" contextid="Button6" macroguid="{A1FEC5BC-9A8A-49C5-B085-0E2EDCEF1F55}"/>
      <assignment backup="false" original="false" shiftstate="1" contextid="Button8" macroguid="{68A1C0B2-2996-4992-9CC5-3285AC8E9740}"/>
      <assignment backup="false" original="false" shiftstate="4" contextid="Button1" macroguid="{5DAFA657-7E0B-4D37-9F7A-FA252ED551E6}"/>
      <assignment backup="false" original="false" shiftstate="4" contextid="Button2" macroguid="{9D0F4485-F6CE-49AF-B3FB-328DBF996F1E}"/>
      <assignment backup="false" original="false" shiftstate="4" contextid="Button3" macroguid="{8B615B23-6FDC-4430-9E57-E5CCBCAC4575}"/>
      <assignment backup="false" original="false" shiftstate="4" contextid="Button4" macroguid="{A0D817F6-1D5D-483B-ADD0-2634CD93D42A}"/>
      <assignment backup="false" original="false" shiftstate="4" contextid="Button5" macroguid="{8B13562D-60F2-460F-9588-8C84168C81BC}"/>
      <assignment backup="false" original="false" shiftstate="4" contextid="Button6" macroguid="{A1FEC5BC-9A8A-49C5-B085-0E2EDCEF1F55}"/>
      <assignment backup="false" original="false" shiftstate="4" contextid="Button7" macroguid="{12C9716B-4D7A-4F6F-AF20-A0369219119A}"/>
      <assignment backup="false" original="false" shiftstate="4" contextid="Button8" macroguid="{68A1C0B2-2996-4992-9CC5-3285AC8E9740}"/>
      <assignment backup="false" original="false" shiftstate="4" contextid="Button10" macroguid="{C0C50E2E-DC80-4C90-85E7-D3FAA614A39E}"/>
      <assignment backup="false" original="false" shiftstate="4" contextid="Button11" macroguid="{EE4405FC-1722-4567-A8D3-A2E2A55FDB4F}"/>
      <assignment backup="false" original="false" shiftstate="1" contextid="Button7" macroguid="{A0D817F6-1D5D-483B-ADD0-2634CD93D42A}"/>
      <assignment backup="false" original="false" shiftstate="1" contextid="Button4" macroguid="{12C9716B-4D7A-4F6F-AF20-A0369219119A}"/>
      <assignment backup="false" original="false" shiftstate="1" contextid="Button9" macroguid="{9D0036D1-FF58-4DCF-B8FB-17940F29BB6F}"/>
    </assignments>
    <pointers>
      <pointer devicemodel="Logitech.Gaming.Mouse.C08B">
        <mode shiftstate="1">
          <reportrate rate="1000"/>
          <powermode value="2"/>
          <dpitable defaultindex="0" syncxy="1" shiftindex="0">
            <dpi enabled="1" x="800" y="800"/>
          </dpitable>
          <movement acceleration="0" speed="-1"/>
        </mode>
      </pointer>
    </pointers>
    <backlight devicemodel="Logitech.Gaming.Mouse.C08B">
      <lightingsetting><![CDATA[{"zones":{"1":{"color":"#000000","effectid":3,"intensity":100,"param":0,"rate":8000},"2":{"color":"#000000","effectid":3,"intensity":100,"param":0,"rate":8000}}}]]></lightingsetting>
    </backlight>
    <script>function OnEvent(event, arg)
    OutputLogMessage("event = %s, arg = %s\n", event, arg)
end</script>
  </profile>
</profiles>
